QtPyConvert-3.1.0.data/scripts/qresource_convert
QtPyConvert-3.1.0.data/scripts/qt_py_convert
QtPyConvert-3.1.0.dist-info/DESCRIPTION.rst
QtPyConvert-3.1.0.dist-info/METADATA
QtPyConvert-3.1.0.dist-info/RECORD
QtPyConvert-3.1.0.dist-info/WHEEL
QtPyConvert-3.1.0.dist-info/metadata.json
QtPyConvert-3.1.0.dist-info/top_level.txt
qt_py_convert/__init__.py
qt_py_convert/color.py
qt_py_convert/diff.py
qt_py_convert/general.py
qt_py_convert/log.py
qt_py_convert/mappings.py
qt_py_convert/run.py
qt_py_convert/_modules/__init__.py
qt_py_convert/_modules/expand_stars/__init__.py
qt_py_convert/_modules/expand_stars/process.py
qt_py_convert/_modules/from_imports/__init__.py
qt_py_convert/_modules/from_imports/process.py
qt_py_convert/_modules/imports/__init__.py
qt_py_convert/_modules/imports/process.py
qt_py_convert/_modules/psep0101/__init__.py
qt_py_convert/_modules/psep0101/_c_args.py
qt_py_convert/_modules/psep0101/_conversion_methods.py
qt_py_convert/_modules/psep0101/_qsignal.py
qt_py_convert/_modules/psep0101/process.py
qt_py_convert/_modules/unsupported/__init__.py
qt_py_convert/_modules/unsupported/process.py
