Metadata-Version: 2.0
Name: QtPyConvert
Version: 3.1.0
Summary: An automatic Python Qt binding transpiler to the Qt.py abstraction layer. It aims to help in your modernization of your Python Qt code. QtPyConvert supports the following bindings out of the box: PyQt4, PySide, PyQt5, PySide2. It also has experimental support for defining your own bindings.
Home-page: https://github.com/digitaldomain/QtPyConvert
Author: Alex Hughes
Author-email: ahughesalex@gmail.com
License: Modified Apache 2.0
Platform: UNKNOWN
Classifier: Development Status :: 4 - Beta
Classifier: Intended Audience :: Developers
Classifier: License :: OSI Approved :: MIT License
Classifier: Programming Language :: Python
Classifier: Programming Language :: Python :: 2
Classifier: Programming Language :: Python :: 2.6
Classifier: Programming Language :: Python :: 2.7
Classifier: Programming Language :: Python :: 3
Classifier: Programming Language :: Python :: 3.3
Classifier: Programming Language :: Python :: 3.5
Classifier: Topic :: Software Development :: Libraries :: Python Modules
Classifier: Topic :: Utilities
Requires-Dist: Qt.py (>=1.2.0.b2)
Requires-Dist: redbaron
